twobyonemux.v
module cmos_twobyonemux(s,a,b,y);
input s,a,b;
output y;

wire w,w1,w2,w3,w4;

supply0 gnd;
supply1 vdd;

nmos(w1,gnd, s);
pmos(w1,vdd, s);//w1 is complement of s

nmos(w,gnd,a);
nmos(w4,w,w1);

nmos(w2,gnd,b);
nmos(w4,w2,s);

pmos(w3,vdd,w1);
pmos(w3,vdd,a);

pmos(w4,w3,s);
pmos(w4,w3,b);//w4 will have complement of y

nmos(y,gnd,w4);
pmos(y,vdd,w4);

endmodule

fourbyonemux.v
`include "twobyonemux.v"
module cmos_fourbyonemux(s0, s1, a, b, c, d, y);
input s0,s1,a,b,c,d;
output y;

wire w,w1,w2,w3,w4;

supply0 gnd;
supply1 vdd;

cmos_twobyonemux mux1(.s(s0), .a(a), .b(b), .y(w));

nmos(w2,gnd,w);
pmos(w2,vdd,w);

cmos_twobyonemux mux2(.s(s0), .a(c), .b(d), .y(w1));

nmos(w3,gnd,w1);
pmos(w3,vdd,w1);

cmos_twobyonemux mux3(.s(s1), .a(w2), .b(w3), .y(w4));

nmos(y,gnd,w4);
pmos(y,vdd,w4);

endmodule

fourbyonemux_tb.v
`include "fourbyonemux.v"
module fourbyonemux_tb();
reg s0,s1,a1,b1,c1,d1;

wire out;

initial begin
$dumpfile("cmos_fourbyonemux.vcd");
$dumpvars(0,fourbyonemux_tb);
$display("s0,  s1,  in1,  in2,  in3,  in4,  out");
$monitor("%b,   %b,   %b,   %b,  %b,  %b,  %b", s0, s1, a1, b1, c1, d1, out);
#20 s0=0;s1=0;a1=0;b1=0;c1=0;d1=0;
#20 s0=0;s1=0;a1=0;b1=0;c1=0;d1=1;
#20 s0=0;s1=0;a1=0;b1=0;c1=1;d1=0;
#20 s0=0;s1=0;a1=0;b1=0;c1=1;d1=1;

#20 s0=0;s1=0;a1=0;b1=1;c1=0;d1=0;
#20 s0=0;s1=0;a1=0;b1=1;c1=0;d1=1;
#20 s0=0;s1=0;a1=0;b1=1;c1=1;d1=0;
#20 s0=0;s1=0;a1=0;b1=1;c1=1;d1=1;

#20 s0=0;s1=0;a1=1;b1=0;c1=0;d1=0;
#20 s0=0;s1=0;a1=1;b1=0;c1=0;d1=1;
#20 s0=0;s1=0;a1=1;b1=0;c1=1;d1=0;
#20 s0=0;s1=0;a1=1;b1=0;c1=1;d1=1;

#20 s0=0;s1=0;a1=1;b1=1;c1=0;d1=0;
#20 s0=0;s1=0;a1=1;b1=1;c1=0;d1=1;
#20 s0=0;s1=0;a1=1;b1=1;c1=1;d1=0;
#20 s0=0;s1=0;a1=1;b1=1;c1=1;d1=1;



#20 s0=0;s1=1;a1=0;b1=0;c1=0;d1=0;
#20 s0=0;s1=1;a1=0;b1=0;c1=0;d1=1;
#20 s0=0;s1=1;a1=0;b1=0;c1=1;d1=0;
#20 s0=0;s1=1;a1=0;b1=0;c1=1;d1=1;

#20 s0=0;s1=1;a1=0;b1=1;c1=0;d1=0;
#20 s0=0;s1=1;a1=0;b1=1;c1=0;d1=1;
#20 s0=0;s1=1;a1=0;b1=1;c1=1;d1=0;
#20 s0=0;s1=1;a1=0;b1=1;c1=1;d1=1;

#20 s0=0;s1=1;a1=1;b1=0;c1=0;d1=0;
#20 s0=0;s1=1;a1=1;b1=0;c1=0;d1=1;
#20 s0=0;s1=1;a1=1;b1=0;c1=1;d1=0;
#20 s0=0;s1=1;a1=1;b1=0;c1=1;d1=1;

#20 s0=0;s1=1;a1=1;b1=1;c1=0;d1=0;
#20 s0=0;s1=1;a1=1;b1=1;c1=0;d1=1;
#20 s0=0;s1=1;a1=1;b1=1;c1=1;d1=0;
#20 s0=0;s1=1;a1=1;b1=1;c1=1;d1=1;



#20 s0=1;s1=0;a1=0;b1=0;c1=0;d1=0;
#20 s0=1;s1=0;a1=0;b1=0;c1=0;d1=1;
#20 s0=1;s1=0;a1=0;b1=0;c1=1;d1=0;
#20 s0=1;s1=0;a1=0;b1=0;c1=1;d1=1;

#20 s0=1;s1=0;a1=0;b1=1;c1=0;d1=0;
#20 s0=1;s1=0;a1=0;b1=1;c1=0;d1=1;
#20 s0=1;s1=0;a1=0;b1=1;c1=1;d1=0;
#20 s0=1;s1=0;a1=0;b1=1;c1=1;d1=1;

#20 s0=1;s1=0;a1=1;b1=0;c1=0;d1=0;
#20 s0=1;s1=0;a1=1;b1=0;c1=0;d1=1;
#20 s0=1;s1=0;a1=1;b1=0;c1=1;d1=0;
#20 s0=1;s1=0;a1=1;b1=0;c1=1;d1=1;

#20 s0=1;s1=0;a1=1;b1=1;c1=0;d1=0;
#20 s0=1;s1=0;a1=1;b1=1;c1=0;d1=1;
#20 s0=1;s1=0;a1=1;b1=1;c1=1;d1=0;
#20 s0=1;s1=0;a1=1;b1=1;c1=1;d1=1;



#20 s0=1;s1=1;a1=0;b1=0;c1=0;d1=0;
#20 s0=1;s1=1;a1=0;b1=0;c1=0;d1=1;
#20 s0=1;s1=1;a1=0;b1=0;c1=1;d1=0;
#20 s0=1;s1=1;a1=0;b1=0;c1=1;d1=1;

#20 s0=1;s1=1;a1=0;b1=1;c1=0;d1=0;
#20 s0=1;s1=1;a1=0;b1=1;c1=0;d1=1;
#20 s0=1;s1=1;a1=0;b1=1;c1=1;d1=0;
#20 s0=1;s1=1;a1=0;b1=1;c1=1;d1=1;

#20 s0=1;s1=1;a1=1;b1=0;c1=0;d1=0;
#20 s0=1;s1=1;a1=1;b1=0;c1=0;d1=1;
#20 s0=1;s1=1;a1=1;b1=0;c1=1;d1=0;
#20 s0=1;s1=1;a1=1;b1=0;c1=1;d1=1;

#20 s0=1;s1=1;a1=1;b1=1;c1=0;d1=0;
#20 s0=1;s1=1;a1=1;b1=1;c1=0;d1=1;
#20 s0=1;s1=1;a1=1;b1=1;c1=1;d1=0;
#20 s0=1;s1=1;a1=1;b1=1;c1=1;d1=1;


#20 $finish;
end


cmos_fourbyonemux n(
.s0(s0),
.s1(s1),
.a(a1),
.b(b1),
.c(c1),
.d(d1),
.y(out)
);

endmodule

cmos_fourbyonemux.vcd
$date
	Thu Nov  8 05:18:56 2018
$end
$version
	Icarus Verilog
$end
$timescale
	1s
$end
$scope module fourbyonemux_tb $end
$var wire 1 ! out $end
$var reg 1 " a1 $end
$var reg 1 # b1 $end
$var reg 1 $ c1 $end
$var reg 1 % d1 $end
$var reg 1 & s0 $end
$var reg 1 ' s1 $end
$scope module n $end
$var wire 1 ( a $end
$var wire 1 ) b $end
$var wire 1 * c $end
$var wire 1 + d $end
$var wire 1 , gnd $end
$var wire 1 - s0 $end
$var wire 1 . s1 $end
$var wire 1 / vdd $end
$var wire 1 0 w $end
$var wire 1 1 w1 $end
$var wire 1 2 w2 $end
$var wire 1 3 w3 $end
$var wire 1 4 w4 $end
$var wire 1 ! y $end
$scope module mux1 $end
$var wire 1 ( a $end
$var wire 1 ) b $end
$var wire 1 5 gnd $end
$var wire 1 - s $end
$var wire 1 6 vdd $end
$var wire 1 7 w $end
$var wire 1 8 w1 $end
$var wire 1 9 w2 $end
$var wire 1 : w3 $end
$var wire 1 ; w4 $end
$var wire 1 0 y $end
$upscope $end
$scope module mux2 $end
$var wire 1 * a $end
$var wire 1 + b $end
$var wire 1 < gnd $end
$var wire 1 - s $end
$var wire 1 = vdd $end
$var wire 1 > w $end
$var wire 1 ? w1 $end
$var wire 1 @ w2 $end
$var wire 1 A w3 $end
$var wire 1 B w4 $end
$var wire 1 1 y $end
$upscope $end
$scope module mux3 $end
$var wire 1 2 a $end
$var wire 1 3 b $end
$var wire 1 C gnd $end
$var wire 1 . s $end
$var wire 1 D vdd $end
$var wire 1 E w $end
$var wire 1 F w1 $end
$var wire 1 G w2 $end
$var wire 1 H w3 $end
$var wire 1 I w4 $end
$var wire 1 4 y $end
$upscope $end
$upscope $end
$upscope $end
$enddefinitions $end
#0
$dumpvars
xI
xH
xG
xF
xE
1D
0C
xB
xA
x@
x?
x>
1=
0<
x;
x:
x9
x8
x7
16
05
x4
x3
x2
x1
x0
1/
x.
x-
0,
x+
x*
x)
x(
x'
x&
x%
x$
x#
x"
x!
$end
#20
0%
0+
z@
0$
0*
13
0G
01
1B
z>
1A
0#
0)
z9
0"
0(
12
0!
14
0E
0I
zH
00
1;
z7
1:
0'
0.
1F
0&
0-
18
1?
#40
1%
1+
0@
#60
0%
0+
z@
1$
1*
0>
03
zG
11
0B
zA
#80
1%
1+
0@
#100
0%
0+
z@
0$
0*
z>
13
0G
01
1B
1A
1#
1)
09
#120
1%
1+
0@
#140
0%
0+
z@
1$
1*
0>
03
zG
11
0B
zA
#160
1%
1+
0@
#180
0%
0+
z@
0$
0*
z>
13
0G
01
1B
1A
0#
0)
z9
1"
1(
07
02
zE
1!
04
1I
1H
10
0;
z:
#200
1%
1+
0@
#220
0%
0+
z@
1$
1*
0>
03
zG
11
0B
zA
#240
1%
1+
0@
#260
0%
0+
z@
0$
0*
z>
13
0G
01
1B
1A
1#
1)
09
#280
1%
1+
0@
#300
0%
0+
z@
1$
1*
0>
03
zG
11
0B
zA
#320
1%
1+
0@
#340
0%
0+
z@
0$
0*
z>
13
0G
0!
14
0I
01
1B
1A
0#
0)
z9
0"
0(
z7
12
0E
00
1;
1:
1'
1.
0F
#360
1%
1+
0@
#380
0%
0+
z@
1$
1*
0>
03
zG
1!
04
1I
11
0B
zA
#400
1%
1+
0@
#420
0%
0+
z@
0$
0*
z>
13
0G
0!
14
0I
01
1B
1A
1#
1)
09
#440
1%
1+
0@
#460
0%
0+
z@
1$
1*
0>
03
zG
1!
04
1I
11
0B
zA
#480
1%
1+
0@
#500
0%
0+
z@
0$
0*
z>
13
0G
0!
14
0I
01
1B
1A
0#
0)
z9
1"
1(
07
02
zE
10
0;
z:
#520
1%
1+
0@
#540
0%
0+
z@
1$
1*
0>
03
zG
1!
04
1I
11
0B
zA
#560
1%
1+
0@
#580
0%
0+
z@
0$
0*
z>
13
0G
0!
14
0I
01
1B
1A
1#
1)
09
#600
1%
1+
0@
#620
0%
0+
z@
1$
1*
0>
03
zG
1!
04
1I
11
0B
zA
#640
1%
1+
0@
#660
0%
0+
z@
13
0G
01
1B
0$
0*
z>
0#
0)
z9
12
0E
0!
14
0I
zH
00
1;
0"
0(
z7
0'
0.
1F
1&
1-
1:
08
1A
0?
#680
1%
1+
0@
03
zG
11
0B
#700
0%
0+
z@
13
0G
01
1B
1$
1*
0>
#720
1%
1+
0@
03
zG
11
0B
#740
0%
0+
z@
13
0G
01
1B
0$
0*
z>
1#
1)
09
02
zE
1!
04
1I
1H
10
0;
#760
1%
1+
0@
03
zG
11
0B
#780
0%
0+
z@
13
0G
01
1B
1$
1*
0>
#800
1%
1+
0@
03
zG
11
0B
#820
0%
0+
z@
13
0G
01
1B
0$
0*
z>
0#
0)
z9
12
0E
0!
14
0I
zH
00
1;
1"
1(
07
#840
1%
1+
0@
03
zG
11
0B
#860
0%
0+
z@
13
0G
01
1B
1$
1*
0>
#880
1%
1+
0@
03
zG
11
0B
#900
0%
0+
z@
13
0G
01
1B
0$
0*
z>
1#
1)
09
02
zE
1!
04
1I
1H
10
0;
#920
1%
1+
0@
03
zG
11
0B
#940
0%
0+
z@
13
0G
01
1B
1$
1*
0>
#960
1%
1+
0@
03
zG
11
0B
#980
0%
0+
z@
13
0G
0!
14
0I
01
1B
0$
0*
z>
0#
0)
z9
12
0E
00
1;
0"
0(
z7
1'
1.
0F
#1000
1%
1+
0@
03
zG
1!
04
1I
11
0B
#1020
0%
0+
z@
13
0G
0!
14
0I
01
1B
1$
1*
0>
#1040
1%
1+
0@
03
zG
1!
04
1I
11
0B
#1060
0%
0+
z@
13
0G
0!
14
0I
01
1B
0$
0*
z>
1#
1)
09
02
zE
10
0;
#1080
1%
1+
0@
03
zG
1!
04
1I
11
0B
#1100
0%
0+
z@
13
0G
0!
14
0I
01
1B
1$
1*
0>
#1120
1%
1+
0@
03
zG
1!
04
1I
11
0B
#1140
0%
0+
z@
13
0G
0!
14
0I
01
1B
0$
0*
z>
0#
0)
z9
12
0E
00
1;
1"
1(
07
#1160
1%
1+
0@
03
zG
1!
04
1I
11
0B
#1180
0%
0+
z@
13
0G
0!
14
0I
01
1B
1$
1*
0>
#1200
1%
1+
0@
03
zG
1!
04
1I
11
0B
#1220
0%
0+
z@
13
0G
0!
14
0I
01
1B
0$
0*
z>
1#
1)
09
02
zE
10
0;
#1240
1%
1+
0@
03
zG
1!
04
1I
11
0B
#1260
0%
0+
z@
13
0G
0!
14
0I
01
1B
1$
1*
0>
#1280
1%
1+
0@
03
zG
1!
04
1I
11
0B
