twobyonemux.v
module cmos_twobyonemux(s,a,b,y);
input s,a,b;
output y;

wire w,w1,w2,w3,w4;

supply0 gnd;
supply1 vdd;

nmos(w1,gnd, s);
pmos(w1,vdd, s);//w1 is complement of s

nmos(w,gnd,a);
nmos(w4,w,w1);

nmos(w2,gnd,b);
nmos(w4,w2,s);

pmos(w3,vdd,w1);
pmos(w3,vdd,a);

pmos(w4,w3,s);
pmos(w4,w3,b);//w4 will have complement of y

nmos(y,gnd,w4);
pmos(y,vdd,w4);

endmodule

twobyonemux_tb.v
`include "twobyonemux.v"
module twobyonemux_tb();
reg s1,a1,b1;

wire out;

initial begin
$dumpfile("cmos_twobyonemux.vcd");
$dumpvars(0,twobyonemux_tb);
$display("s1,in1,in2,out");
$monitor("%b, %b, %b, %b", s1, a1, b1, out);
#20 s1=0;a1=0;b1=0;
#20 s1=0;a1=0;b1=1;
#20 s1=0;a1=1;b1=0;
#20 s1=0;a1=1;b1=1;
#20 s1=1;a1=0;b1=0;
#20 s1=1;a1=0;b1=1;
#20 s1=1;a1=1;b1=0;
#20 s1=1;a1=1;b1=1;
#20 $finish;
end


cmos_twobyonemux n(
.s(s1),
.a(a1),
.b(b1),
.y(out)
);

endmodule

cmos_twobyonemux.vcd
$date
	Thu Nov  8 05:13:34 2018
$end
$version
	Icarus Verilog
$end
$timescale
	1s
$end
$scope module twobyonemux_tb $end
$var wire 1 ! out $end
$var reg 1 " a1 $end
$var reg 1 # b1 $end
$var reg 1 $ s1 $end
$scope module n $end
$var wire 1 % a $end
$var wire 1 & b $end
$var wire 1 ' gnd $end
$var wire 1 ( s $end
$var wire 1 ) vdd $end
$var wire 1 * w $end
$var wire 1 + w1 $end
$var wire 1 , w2 $end
$var wire 1 - w3 $end
$var wire 1 . w4 $end
$var wire 1 ! y $end
$upscope $end
$upscope $end
$enddefinitions $end
#0
$dumpvars
x.
x-
x,
x+
x*
1)
x(
0'
x&
x%
x$
x#
x"
x!
$end
#20
0#
z,
0&
0"
0!
1.
z*
1-
0%
0$
1+
0(
#40
1#
0,
1&
#60
0#
z,
0&
1"
0*
1!
0.
z-
1%
#80
1#
0,
1&
#100
0#
z,
0!
1.
0&
0"
z*
0%
1$
1-
0+
1(
#120
1#
0,
1!
0.
1&
#140
0#
z,
0!
1.
0&
1"
0*
1%
#160
1#
0,
1!
0.
1&
