fourbyonemuxtrans.v
module cmos_fourbyonemuxtrans(a,b,c,d,s0,s1,z);
input a,b,c,d,s0,s1;
output z;
wire c1,c2,x,y;
supply0 gnd;
supply1 vdd;

//complement s0
pmos(c1,vdd,s0);
nmos(c1,gnd,s0);

//complement s1
pmos(c2,vdd,s1);
nmos(c2,gnd,s1);

pmos(x,a,c2);
nmos(x,a,s1);

pmos(x,b,s1);
nmos(x,b,c2);

pmos(y,c,c2);
nmos(y,c,s1);

pmos(y,d,s1);
nmos(y,d,c2);

pmos(z,x,c1);
nmos(z,x,s0);

pmos(z,y,s0);
nmos(z,y,c1);

endmodule

fourbyonemuxtrans_tb.v
`include "fourbyonemuxtrans.v"

module fourbyonemuxtranstb();
reg a1,b1,c1,d1,s0,s1;
wire out;
initial begin
$dumpfile("fourbyonemuxtrans_tb.vcd");
$dumpvars(0,fourbyonemuxtranstb);
$display("in1,in2,in3,in4,gate1,gate2,out");
$monitor("%b,%b,%b,%b,%b,%b,%b",a1,b1,c1,d1,s0,s1,out);

#20 s0=0;s1=0;a1=0;b1=0;c1=0;d1=0;
#20 s0=0;s1=0;a1=0;b1=0;c1=0;d1=1;
#20 s0=0;s1=0;a1=0;b1=0;c1=1;d1=0;
#20 s0=0;s1=0;a1=0;b1=0;c1=1;d1=1;

#20 s0=0;s1=0;a1=0;b1=1;c1=0;d1=0;
#20 s0=0;s1=0;a1=0;b1=1;c1=0;d1=1;
#20 s0=0;s1=0;a1=0;b1=1;c1=1;d1=0;
#20 s0=0;s1=0;a1=0;b1=1;c1=1;d1=1;

#20 s0=0;s1=0;a1=1;b1=0;c1=0;d1=0;
#20 s0=0;s1=0;a1=1;b1=0;c1=0;d1=1;
#20 s0=0;s1=0;a1=1;b1=0;c1=1;d1=0;
#20 s0=0;s1=0;a1=1;b1=0;c1=1;d1=1;

#20 s0=0;s1=0;a1=1;b1=1;c1=0;d1=0;
#20 s0=0;s1=0;a1=1;b1=1;c1=0;d1=1;
#20 s0=0;s1=0;a1=1;b1=1;c1=1;d1=0;
#20 s0=0;s1=0;a1=1;b1=1;c1=1;d1=1;



#20 s0=0;s1=1;a1=0;b1=0;c1=0;d1=0;
#20 s0=0;s1=1;a1=0;b1=0;c1=0;d1=1;
#20 s0=0;s1=1;a1=0;b1=0;c1=1;d1=0;
#20 s0=0;s1=1;a1=0;b1=0;c1=1;d1=1;

#20 s0=0;s1=1;a1=0;b1=1;c1=0;d1=0;
#20 s0=0;s1=1;a1=0;b1=1;c1=0;d1=1;
#20 s0=0;s1=1;a1=0;b1=1;c1=1;d1=0;
#20 s0=0;s1=1;a1=0;b1=1;c1=1;d1=1;

#20 s0=0;s1=1;a1=1;b1=0;c1=0;d1=0;
#20 s0=0;s1=1;a1=1;b1=0;c1=0;d1=1;
#20 s0=0;s1=1;a1=1;b1=0;c1=1;d1=0;
#20 s0=0;s1=1;a1=1;b1=0;c1=1;d1=1;

#20 s0=0;s1=1;a1=1;b1=1;c1=0;d1=0;
#20 s0=0;s1=1;a1=1;b1=1;c1=0;d1=1;
#20 s0=0;s1=1;a1=1;b1=1;c1=1;d1=0;
#20 s0=0;s1=1;a1=1;b1=1;c1=1;d1=1;



#20 s0=1;s1=0;a1=0;b1=0;c1=0;d1=0;
#20 s0=1;s1=0;a1=0;b1=0;c1=0;d1=1;
#20 s0=1;s1=0;a1=0;b1=0;c1=1;d1=0;
#20 s0=1;s1=0;a1=0;b1=0;c1=1;d1=1;

#20 s0=1;s1=0;a1=0;b1=1;c1=0;d1=0;
#20 s0=1;s1=0;a1=0;b1=1;c1=0;d1=1;
#20 s0=1;s1=0;a1=0;b1=1;c1=1;d1=0;
#20 s0=1;s1=0;a1=0;b1=1;c1=1;d1=1;

#20 s0=1;s1=0;a1=1;b1=0;c1=0;d1=0;
#20 s0=1;s1=0;a1=1;b1=0;c1=0;d1=1;
#20 s0=1;s1=0;a1=1;b1=0;c1=1;d1=0;
#20 s0=1;s1=0;a1=1;b1=0;c1=1;d1=1;

#20 s0=1;s1=0;a1=1;b1=1;c1=0;d1=0;
#20 s0=1;s1=0;a1=1;b1=1;c1=0;d1=1;
#20 s0=1;s1=0;a1=1;b1=1;c1=1;d1=0;
#20 s0=1;s1=0;a1=1;b1=1;c1=1;d1=1;



#20 s0=1;s1=1;a1=0;b1=0;c1=0;d1=0;
#20 s0=1;s1=1;a1=0;b1=0;c1=0;d1=1;
#20 s0=1;s1=1;a1=0;b1=0;c1=1;d1=0;
#20 s0=1;s1=1;a1=0;b1=0;c1=1;d1=1;

#20 s0=1;s1=1;a1=0;b1=1;c1=0;d1=0;
#20 s0=1;s1=1;a1=0;b1=1;c1=0;d1=1;
#20 s0=1;s1=1;a1=0;b1=1;c1=1;d1=0;
#20 s0=1;s1=1;a1=0;b1=1;c1=1;d1=1;

#20 s0=1;s1=1;a1=1;b1=0;c1=0;d1=0;
#20 s0=1;s1=1;a1=1;b1=0;c1=0;d1=1;
#20 s0=1;s1=1;a1=1;b1=0;c1=1;d1=0;
#20 s0=1;s1=1;a1=1;b1=0;c1=1;d1=1;

#20 s0=1;s1=1;a1=1;b1=1;c1=0;d1=0;
#20 s0=1;s1=1;a1=1;b1=1;c1=0;d1=1;
#20 s0=1;s1=1;a1=1;b1=1;c1=1;d1=0;
#20 s0=1;s1=1;a1=1;b1=1;c1=1;d1=1;

#20 $finish;
end

cmos_fourbyonemuxtrans n(
.a(a1),
.b(b1),
.c(c1),
.d(d1),
.s0(s0),
.s1(s1),
.z(out)
);
endmodule

fourbyonemuxtrans_tb.vcd
$date
	Thu Nov  8 05:01:29 2018
$end
$version
	Icarus Verilog
$end
$timescale
	1s
$end
$scope module fourbyonemuxtranstb $end
$var wire 1 ! out $end
$var reg 1 " a1 $end
$var reg 1 # b1 $end
$var reg 1 $ c1 $end
$var reg 1 % d1 $end
$var reg 1 & s0 $end
$var reg 1 ' s1 $end
$scope module n $end
$var wire 1 ( a $end
$var wire 1 ) b $end
$var wire 1 * c $end
$var wire 1 + c1 $end
$var wire 1 , c2 $end
$var wire 1 - d $end
$var wire 1 . gnd $end
$var wire 1 / s0 $end
$var wire 1 0 s1 $end
$var wire 1 1 vdd $end
$var wire 1 2 x $end
$var wire 1 3 y $end
$var wire 1 ! z $end
$upscope $end
$upscope $end
$enddefinitions $end
#0
$dumpvars
x3
x2
11
x0
x/
0.
x-
x,
x+
x*
x)
x(
x'
x&
x%
x$
x#
x"
x!
$end
#20
0%
0!
03
0-
0$
0*
0#
02
0)
0"
0(
0'
1,
00
0&
1+
0/
#40
1%
1!
13
1-
#60
0%
0!
03
0-
1$
1*
#80
1%
1!
13
1-
#100
0%
0!
03
0-
0$
0*
1#
12
1)
#120
1%
1!
13
1-
#140
0%
0!
03
0-
1$
1*
#160
1%
1!
13
1-
#180
0%
0!
03
0-
0$
0*
0#
02
0)
1"
1(
#200
1%
1!
13
1-
#220
0%
0!
03
0-
1$
1*
#240
1%
1!
13
1-
#260
0%
0!
03
0-
0$
0*
1#
12
1)
#280
1%
1!
13
1-
#300
0%
0!
03
0-
1$
1*
#320
1%
1!
13
1-
#340
0%
0-
0$
0!
03
0*
0#
0)
0"
02
0(
1'
0,
10
#360
1%
1-
#380
0%
0-
1$
1!
13
1*
#400
1%
1-
#420
0%
0-
0$
0!
03
0*
1#
1)
#440
1%
1-
#460
0%
0-
1$
1!
13
1*
#480
1%
1-
#500
0%
0-
0$
0!
03
0*
0#
0)
1"
12
1(
#520
1%
1-
#540
0%
0-
1$
1!
13
1*
#560
1%
1-
#580
0%
0-
0$
0!
03
0*
1#
1)
#600
1%
1-
#620
0%
0-
1$
1!
13
1*
#640
1%
1-
#660
0%
03
0-
0$
0*
0#
0!
02
0)
0"
0(
0'
1,
00
1&
0+
1/
#680
1%
13
1-
#700
0%
03
0-
1$
1*
#720
1%
13
1-
#740
0%
03
0-
0$
0*
1#
1!
12
1)
#760
1%
13
1-
#780
0%
03
0-
1$
1*
#800
1%
13
1-
#820
0%
03
0-
0$
0*
0#
0!
02
0)
1"
1(
#840
1%
13
1-
#860
0%
03
0-
1$
1*
#880
1%
13
1-
#900
0%
03
0-
0$
0*
1#
1!
12
1)
#920
1%
13
1-
#940
0%
03
0-
1$
1*
#960
1%
13
1-
#980
0%
0-
0$
03
0*
0#
0)
0"
0!
02
0(
1'
0,
10
#1000
1%
1-
#1020
0%
0-
1$
13
1*
#1040
1%
1-
#1060
0%
0-
0$
03
0*
1#
1)
#1080
1%
1-
#1100
0%
0-
1$
13
1*
#1120
1%
1-
#1140
0%
0-
0$
03
0*
0#
0)
1"
1!
12
1(
#1160
1%
1-
#1180
0%
0-
1$
13
1*
#1200
1%
1-
#1220
0%
0-
0$
03
0*
1#
1)
#1240
1%
1-
#1260
0%
0-
1$
13
1*
#1280
1%
1-
