fulladder.v
module cmos_fulladder(a,b,c,s,o);
input a,b,c;
output s,o;
wire w,w1,w2,w3,w4,m,m1,m2,m3,m4,m5,m6,c1,c2,c3,c4,x,y,z;
supply0 gnd;
supply1 vdd;

//complement a
pmos(c1,vdd,a);		
nmos(c1,gnd,a);

//complement b
pmos(c2,vdd,b);
nmos(c2,gnd,b);

//complement c
pmos(c4,vdd,c);
nmos(c4,gnd,c);

//complement x
pmos(c3,vdd,x);
nmos(c3,gnd,x);

//xor of a and b
nmos(w1,gnd,b);
nmos(x,w1,a);

nmos(w,gnd,c2);
nmos(x,w,c1);

pmos(w2,vdd,a);
pmos(w2,vdd,b);

pmos(x,w2,c1);
pmos(x,w2,c2);

//xor of output of xor(a and b) and c
nmos(m1,gnd,c);
nmos(s,m1,x);

nmos(m,gnd,c4);
nmos(s,m,c3);

pmos(m2,vdd,x);
pmos(m2,vdd,c);

pmos(s,m2,c3);
pmos(s,m2,c4);

//and of a and b
nmos(w3,gnd,b);
nmos(w4,w3,a);
pmos(w4,vdd,b);
pmos(w4,vdd,a);
nmos(y,gnd,w4);
pmos(y,vdd,w4);

//and of output of and(a and b) and c
nmos(m3,gnd,c);
nmos(m4,m3,x);
pmos(m4,vdd,c);
pmos(m4,vdd,x);
nmos(z,gnd,m4);
pmos(z,vdd,m4);

//or of the output of both and gates
nmos(m6,gnd,z);
nmos(m6,gnd,y);

pmos(m5,vdd,z);
pmos(m6,m5,y);

nmos(o,gnd,m6);
pmos(o,vdd,m6);

endmodule

fulladdertest.v
`include "fulladder.v"

module fulladdertb();
reg a1,b1,c1;
wire sum,carry;
initial begin
$dumpfile("fulladdertest.vcd");
$dumpvars(0,fulladdertb);
$display("in1,in2,in3,sum,carry");
$monitor("%b,%b,%b,%b,%b",a1,b1,c1,sum,carry);
#20 a1=0;b1=0;c1=0;
#20 a1=1;b1=0;c1=0;
#20 a1=0;b1=1;c1=0;
#20 a1=1;b1=1;c1=0;
#20 a1=0;b1=0;c1=1;
#20 a1=1;b1=0;c1=1;
#20 a1=0;b1=1;c1=1;
#20 a1=1;b1=1;c1=1;
#20 $finish;
end

cmos_fulladder n(
.a(a1),
.b(b1),
.c(c1),
.s(sum),
.o(carry)
);
endmodule

fulladdertest.vcd
$date
	Thu Sep  6 21:03:13 2018
$end
$version
	Icarus Verilog
$end
$timescale
	1s
$end
$scope module fulladdertb $end
$var wire 1 ! carry $end
$var wire 1 " sum $end
$var reg 1 # a1 $end
$var reg 1 $ b1 $end
$var reg 1 % c1 $end
$scope module n $end
$var wire 1 & a $end
$var wire 1 ' b $end
$var wire 1 ( c $end
$var wire 1 ) c1 $end
$var wire 1 * c2 $end
$var wire 1 + c3 $end
$var wire 1 , c4 $end
$var wire 1 - gnd $end
$var wire 1 . m $end
$var wire 1 / m1 $end
$var wire 1 0 m2 $end
$var wire 1 1 m3 $end
$var wire 1 2 m4 $end
$var wire 1 3 m5 $end
$var wire 1 4 m6 $end
$var wire 1 ! o $end
$var wire 1 " s $end
$var wire 1 5 vdd $end
$var wire 1 6 w $end
$var wire 1 7 w1 $end
$var wire 1 8 w2 $end
$var wire 1 9 w3 $end
$var wire 1 : w4 $end
$var wire 1 ; x $end
$var wire 1 < y $end
$var wire 1 = z $end
$upscope $end
$upscope $end
$enddefinitions $end
#0
$dumpvars
x=
x<
x;
x:
x9
x8
x7
x6
15
x4
x3
x2
x1
x0
x/
x.
0-
x,
x+
x*
x)
x(
x'
x&
x%
x$
x#
x"
x!
$end
#20
0%
0.
0"
1,
z/
z1
0(
0$
1+
10
0!
14
13
0=
12
06
0;
1*
z7
z9
0'
0#
1)
18
0<
1:
0&
#40
1#
1"
0+
1;
0)
1&
#60
1$
z6
0*
07
09
1'
0#
1"
0+
1;
1)
0&
#80
1#
0)
0"
1+
0;
z8
1!
04
1<
0:
1&
#100
1%
z.
0,
0/
01
1(
0$
06
1*
z7
z9
0'
0#
1)
1"
1+
0;
18
0!
14
0<
1:
0&
#120
1#
0+
0"
z0
1!
04
z3
1=
02
1;
0)
1&
#140
1$
z6
0*
07
09
1'
0#
0+
0"
z0
1!
04
z3
1=
02
1;
1)
0&
#160
1#
0)
1+
1"
10
13
0=
12
0;
z8
1<
0:
1&
