ms.v
module jkms(q,q_bar,clk,j,k);
	output q,q_bar;
	input clk,j,k;
	reg tq,q,q_bar;

	always @(clk)
	begin

	if (!clk)
	begin
	if (j==1'b0 && k==1'b1)
				tq <= 1'b0;

	else if (j==1'b1 && k==1'b0)
				tq <= 1'b1;

	else if (j==1'b1 && k==1'b1)
				tq <= ~tq;

	end
	if (clk)
	begin

		q <= tq;
		q_bar <= ~tq;

		end
	end
endmodule

ms_tb.v
`include "ms.v"
module jkms_test;
	reg clk,j,k;
      wire q,q_bar;
	wire clk2,j2,k2;
      jkms  inst(q,q_bar,clk,j,k);
      assign clk2=clk;
	assign j2=j;
	assign k2=k;
	initial
               clk = 1'b0;
      always #10
               clk = ~clk;

      initial
      begin
           j = 1'b0; k = 1'b0; 
           #60 j = 1'b0; k = 1'b1;
           #40 j = 1'b1; k = 1'b0;
           #20 j = 1'b1; k = 1'b1;
           #40 j = 1'b1; k = 1'b0;
           #5 j = 1'b0; #20 j = 1'b1;
           #10 $finish;
        end

initial begin
   
   $dumpfile("ms.vcd");
   $dumpvars(0,jkms_test);
   $display("time    clk   j   k   q   q_bar");
   $monitor("%g    %b %b %b %b %b",$time, clk, j, k, q, q_bar);

end

endmodule

ms.vcd
$date
	Thu Nov  8 16:47:20 2018
$end
$version
	Icarus Verilog
$end
$timescale
	1s
$end
$scope module jkms_test $end
$var wire 1 ! clk2 $end
$var wire 1 " j2 $end
$var wire 1 # k2 $end
$var wire 1 $ q $end
$var wire 1 % q_bar $end
$var reg 1 & clk $end
$var reg 1 ' j $end
$var reg 1 ( k $end
$scope module inst $end
$var wire 1 ) clk $end
$var wire 1 * j $end
$var wire 1 + k $end
$var reg 1 , q $end
$var reg 1 - q_bar $end
$var reg 1 . tq $end
$upscope $end
$upscope $end
$enddefinitions $end
#0
$dumpvars
x.
x-
x,
0+
0*
0)
0(
0'
0&
x%
x$
0#
0"
0!
$end
#10
1&
1)
1!
#20
0&
0)
0!
#30
1&
1)
1!
#40
0&
0)
0!
#50
1&
1)
1!
#60
0.
0&
0)
0!
1(
1+
1#
#70
1-
1%
0,
0$
1&
1)
1!
#80
0&
0)
0!
#90
1&
1)
1!
#100
1.
0&
0)
0!
0(
0+
0#
1'
1*
1"
#110
0-
0%
1,
1$
1&
1)
1!
#120
0.
0&
0)
0!
1(
1+
1#
#130
1-
1%
0,
0$
1&
1)
1!
#140
1.
0&
0)
0!
#150
0-
0%
1,
1$
1&
1)
1!
#160
0&
0)
0!
0(
0+
0#
#165
0'
0*
0"
#170
1&
1)
1!
#180
0&
0)
0!
#185
1'
1*
1"
