8bitupdown.v
module bitupdown( clk,enable,reset,mode, count,tc);
input clk,enable,reset,mode;
output reg [7:0]count;
output reg tc;
always @(posedge clk)
begin
	if(enable)
	begin
	if(reset)
	begin
	count=0;
	tc=0;
	end
	if(mode==0)
	begin
	count=count+1;
	if(count==255)
	tc=1;
	else
	tc=0;
	end
	else
	begin
	count=count-1;
	if(count==0)
	tc=1;
	else
	tc=0;
	end
	end
 end
endmodule

8bitupdown_tb.v
`include "8bitupdown.v"
module bitupdowntb;
reg 	CLK,RESET,ENABLE,MODE;
wire[7:0] COUNT_OUT;
wire TC;
initial begin
$dumpfile("testco.vcd");
$dumpvars(0,bitupdowntb);
$display("clk, enable,  reset, mode, count_out, tc");
$monitor("%b,%b,%b,%b,%b,%b",CLK,ENABLE,RESET,MODE,COUNT_OUT,MODE);
CLK=1;
ENABLE=1;
RESET=1;
MODE=0;
#2048 $finish;
end
always #1024 RESET=0;
always #512 MODE=~MODE;
always #1 CLK=~CLK;
 bitupdown ud(.clk(CLK),.enable(ENABLE),.reset(RESET),.mode(MODE),.count(COUNT_OUT),.tc(TC));	

endmodule

testco.vcd
$date
	Thu Nov  8 17:05:06 2018
$end
$version
	Icarus Verilog
$end
$timescale
	1s
$end
$scope module bitupdowntb $end
$var wire 8 ! COUNT_OUT [7:0] $end
$var wire 1 " TC $end
$var reg 1 # CLK $end
$var reg 1 $ ENABLE $end
$var reg 1 % MODE $end
$var reg 1 & RESET $end
$scope module ud $end
$var wire 1 ' clk $end
$var wire 1 ( enable $end
$var wire 1 ) mode $end
$var wire 1 * reset $end
$var reg 8 + count [7:0] $end
$var reg 1 , tc $end
$upscope $end
$upscope $end
$enddefinitions $end
#0
$dumpvars
0,
b1 +
1*
0)
1(
1'
1&
0%
1$
1#
0"
b1 !
$end
#1
0#
0'
#2
b1 +
b1 !
1#
1'
#3
0#
0'
#4
b1 +
b1 !
1#
1'
#5
0#
0'
#6
b1 +
b1 !
1#
1'
#7
0#
0'
#8
b1 +
b1 !
1#
1'
#9
0#
0'
#10
b1 +
b1 !
1#
1'
#11
0#
0'
#12
b1 +
b1 !
1#
1'
#13
0#
0'
#14
b1 +
b1 !
1#
1'
#15
0#
0'
#16
b1 +
b1 !
1#
1'
#17
0#
0'
#18
b1 +
b1 !
1#
1'
#19
0#
0'
#20
b1 +
b1 !
1#
1'
#21
0#
0'
#22
b1 +
b1 !
1#
1'
#23
0#
0'
#24
b1 +
b1 !
1#
1'
#25
0#
0'
#26
b1 +
b1 !
1#
1'
#27
0#
0'
#28
b1 +
b1 !
1#
1'
#29
0#
0'
#30
b1 +
b1 !
1#
1'
#31
0#
0'
#32
b1 +
b1 !
1#
1'
#33
0#
0'
#34
b1 +
b1 !
1#
1'
#35
0#
0'
#36
b1 +
b1 !
1#
1'
#37
0#
0'
#38
b1 +
b1 !
1#
1'
#39
0#
0'
#40
b1 +
b1 !
1#
1'
#41
0#
0'
#42
b1 +
b1 !
1#
1'
#43
0#
0'
#44
b1 +
b1 !
1#
1'
#45
0#
0'
#46
b1 +
b1 !
1#
1'
#47
0#
0'
#48
b1 +
b1 !
1#
1'
#49
0#
0'
#50
b1 +
b1 !
1#
1'
#51
0#
0'
#52
b1 +
b1 !
1#
1'
#53
0#
0'
#54
b1 +
b1 !
1#
1'
#55
0#
0'
#56
b1 +
b1 !
1#
1'
#57
0#
0'
#58
b1 +
b1 !
1#
1'
#59
0#
0'
#60
b1 +
b1 !
1#
1'
#61
0#
0'
#62
b1 +
b1 !
1#
1'
#63
0#
0'
#64
b1 +
b1 !
1#
1'
#65
0#
0'
#66
b1 +
b1 !
1#
1'
#67
0#
0'
#68
b1 +
b1 !
1#
1'
#69
0#
0'
#70
b1 +
b1 !
1#
1'
#71
0#
0'
#72
b1 +
b1 !
1#
1'
#73
0#
0'
#74
b1 +
b1 !
1#
1'
#75
0#
0'
#76
b1 +
b1 !
1#
1'
#77
0#
0'
#78
b1 +
b1 !
1#
1'
#79
0#
0'
#80
b1 +
b1 !
1#
1'
#81
0#
0'
#82
b1 +
b1 !
1#
1'
#83
0#
0'
#84
b1 +
b1 !
1#
1'
#85
0#
0'
#86
b1 +
b1 !
1#
1'
#87
0#
0'
#88
b1 +
b1 !
1#
1'
#89
0#
0'
#90
b1 +
b1 !
1#
1'
#91
0#
0'
#92
b1 +
b1 !
1#
1'
#93
0#
0'
#94
b1 +
b1 !
1#
1'
#95
0#
0'
#96
b1 +
b1 !
1#
1'
#97
0#
0'
#98
b1 +
b1 !
1#
1'
#99
0#
0'
#100
b1 +
b1 !
1#
1'
#101
0#
0'
#102
b1 +
b1 !
1#
1'
#103
0#
0'
#104
b1 +
b1 !
1#
1'
#105
0#
0'
#106
b1 +
b1 !
1#
1'
#107
0#
0'
#108
b1 +
b1 !
1#
1'
#109
0#
0'
#110
b1 +
b1 !
1#
1'
#111
0#
0'
#112
b1 +
b1 !
1#
1'
#113
0#
0'
#114
b1 +
b1 !
1#
1'
#115
0#
0'
#116
b1 +
b1 !
1#
1'
#117
0#
0'
#118
b1 +
b1 !
1#
1'
#119
0#
0'
#120
b1 +
b1 !
1#
1'
#121
0#
0'
#122
b1 +
b1 !
1#
1'
#123
0#
0'
#124
b1 +
b1 !
1#
1'
#125
0#
0'
#126
b1 +
b1 !
1#
1'
#127
0#
0'
#128
b1 +
b1 !
1#
1'
#129
0#
0'
#130
b1 +
b1 !
1#
1'
#131
0#
0'
#132
b1 +
b1 !
1#
1'
#133
0#
0'
#134
b1 +
b1 !
1#
1'
#135
0#
0'
#136
b1 +
b1 !
1#
1'
#137
0#
0'
#138
b1 +
b1 !
1#
1'
#139
0#
0'
#140
b1 +
b1 !
1#
1'
#141
0#
0'
#142
b1 +
b1 !
1#
1'
#143
0#
0'
#144
b1 +
b1 !
1#
1'
#145
0#
0'
#146
b1 +
b1 !
1#
1'
#147
0#
0'
#148
b1 +
b1 !
1#
1'
#149
0#
0'
#150
b1 +
b1 !
1#
1'
#151
0#
0'
#152
b1 +
b1 !
1#
1'
#153
0#
0'
#154
b1 +
b1 !
1#
1'
#155
0#
0'
#156
b1 +
b1 !
1#
1'
#157
0#
0'
#158
b1 +
b1 !
1#
1'
#159
0#
0'
#160
b1 +
b1 !
1#
1'
#161
0#
0'
#162
b1 +
b1 !
1#
1'
#163
0#
0'
#164
b1 +
b1 !
1#
1'
#165
0#
0'
#166
b1 +
b1 !
1#
1'
#167
0#
0'
#168
b1 +
b1 !
1#
1'
#169
0#
0'
#170
b1 +
b1 !
1#
1'
#171
0#
0'
#172
b1 +
b1 !
1#
1'
#173
0#
0'
#174
b1 +
b1 !
1#
1'
#175
0#
0'
#176
b1 +
b1 !
1#
1'
#177
0#
0'
#178
b1 +
b1 !
1#
1'
#179
0#
0'
#180
b1 +
b1 !
1#
1'
#181
0#
0'
#182
b1 +
b1 !
1#
1'
#183
0#
0'
#184
b1 +
b1 !
1#
1'
#185
0#
0'
#186
b1 +
b1 !
1#
1'
#187
0#
0'
#188
b1 +
b1 !
1#
1'
#189
0#
0'
#190
b1 +
b1 !
1#
1'
#191
0#
0'
#192
b1 +
b1 !
1#
1'
#193
0#
0'
#194
b1 +
b1 !
1#
1'
#195
0#
0'
#196
b1 +
b1 !
1#
1'
#197
0#
0'
#198
b1 +
b1 !
1#
1'
#199
0#
0'
#200
b1 +
b1 !
1#
1'
#201
0#
0'
#202
b1 +
b1 !
1#
1'
#203
0#
0'
#204
b1 +
b1 !
1#
1'
#205
0#
0'
#206
b1 +
b1 !
1#
1'
#207
0#
0'
#208
b1 +
b1 !
1#
1'
#209
0#
0'
#210
b1 +
b1 !
1#
1'
#211
0#
0'
#212
b1 +
b1 !
1#
1'
#213
0#
0'
#214
b1 +
b1 !
1#
1'
#215
0#
0'
#216
b1 +
b1 !
1#
1'
#217
0#
0'
#218
b1 +
b1 !
1#
1'
#219
0#
0'
#220
b1 +
b1 !
1#
1'
#221
0#
0'
#222
b1 +
b1 !
1#
1'
#223
0#
0'
#224
b1 +
b1 !
1#
1'
#225
0#
0'
#226
b1 +
b1 !
1#
1'
#227
0#
0'
#228
b1 +
b1 !
1#
1'
#229
0#
0'
#230
b1 +
b1 !
1#
1'
#231
0#
0'
#232
b1 +
b1 !
1#
1'
#233
0#
0'
#234
b1 +
b1 !
1#
1'
#235
0#
0'
#236
b1 +
b1 !
1#
1'
#237
0#
0'
#238
b1 +
b1 !
1#
1'
#239
0#
0'
#240
b1 +
b1 !
1#
1'
#241
0#
0'
#242
b1 +
b1 !
1#
1'
#243
0#
0'
#244
b1 +
b1 !
1#
1'
#245
0#
0'
#246
b1 +
b1 !
1#
1'
#247
0#
0'
#248
b1 +
b1 !
1#
1'
#249
0#
0'
#250
b1 +
b1 !
1#
1'
#251
0#
0'
#252
b1 +
b1 !
1#
1'
#253
0#
0'
#254
b1 +
b1 !
1#
1'
#255
0#
0'
#256
b1 +
b1 !
1#
1'
#257
0#
0'
#258
b1 +
b1 !
1#
1'
#259
0#
0'
#260
b1 +
b1 !
1#
1'
#261
0#
0'
#262
b1 +
b1 !
1#
1'
#263
0#
0'
#264
b1 +
b1 !
1#
1'
#265
0#
0'
#266
b1 +
b1 !
1#
1'
#267
0#
0'
#268
b1 +
b1 !
1#
1'
#269
0#
0'
#270
b1 +
b1 !
1#
1'
#271
0#
0'
#272
b1 +
b1 !
1#
1'
#273
0#
0'
#274
b1 +
b1 !
1#
1'
#275
0#
0'
#276
b1 +
b1 !
1#
1'
#277
0#
0'
#278
b1 +
b1 !
1#
1'
#279
0#
0'
#280
b1 +
b1 !
1#
1'
#281
0#
0'
#282
b1 +
b1 !
1#
1'
#283
0#
0'
#284
b1 +
b1 !
1#
1'
#285
0#
0'
#286
b1 +
b1 !
1#
1'
#287
0#
0'
#288
b1 +
b1 !
1#
1'
#289
0#
0'
#290
b1 +
b1 !
1#
1'
#291
0#
0'
#292
b1 +
b1 !
1#
1'
#293
0#
0'
#294
b1 +
b1 !
1#
1'
#295
0#
0'
#296
b1 +
b1 !
1#
1'
#297
0#
0'
#298
b1 +
b1 !
1#
1'
#299
0#
0'
#300
b1 +
b1 !
1#
1'
#301
0#
0'
#302
b1 +
b1 !
1#
1'
#303
0#
0'
#304
b1 +
b1 !
1#
1'
#305
0#
0'
#306
b1 +
b1 !
1#
1'
#307
0#
0'
#308
b1 +
b1 !
1#
1'
#309
0#
0'
#310
b1 +
b1 !
1#
1'
#311
0#
0'
#312
b1 +
b1 !
1#
1'
#313
0#
0'
#314
b1 +
b1 !
1#
1'
#315
0#
0'
#316
b1 +
b1 !
1#
1'
#317
0#
0'
#318
b1 +
b1 !
1#
1'
#319
0#
0'
#320
b1 +
b1 !
1#
1'
#321
0#
0'
#322
b1 +
b1 !
1#
1'
#323
0#
0'
#324
b1 +
b1 !
1#
1'
#325
0#
0'
#326
b1 +
b1 !
1#
1'
#327
0#
0'
#328
b1 +
b1 !
1#
1'
#329
0#
0'
#330
b1 +
b1 !
1#
1'
#331
0#
0'
#332
b1 +
b1 !
1#
1'
#333
0#
0'
#334
b1 +
b1 !
1#
1'
#335
0#
0'
#336
b1 +
b1 !
1#
1'
#337
0#
0'
#338
b1 +
b1 !
1#
1'
#339
0#
0'
#340
b1 +
b1 !
1#
1'
#341
0#
0'
#342
b1 +
b1 !
1#
1'
#343
0#
0'
#344
b1 +
b1 !
1#
1'
#345
0#
0'
#346
b1 +
b1 !
1#
1'
#347
0#
0'
#348
b1 +
b1 !
1#
1'
#349
0#
0'
#350
b1 +
b1 !
1#
1'
#351
0#
0'
#352
b1 +
b1 !
1#
1'
#353
0#
0'
#354
b1 +
b1 !
1#
1'
#355
0#
0'
#356
b1 +
b1 !
1#
1'
#357
0#
0'
#358
b1 +
b1 !
1#
1'
#359
0#
0'
#360
b1 +
b1 !
1#
1'
#361
0#
0'
#362
b1 +
b1 !
1#
1'
#363
0#
0'
#364
b1 +
b1 !
1#
1'
#365
0#
0'
#366
b1 +
b1 !
1#
1'
#367
0#
0'
#368
b1 +
b1 !
1#
1'
#369
0#
0'
#370
b1 +
b1 !
1#
1'
#371
0#
0'
#372
b1 +
b1 !
1#
1'
#373
0#
0'
#374
b1 +
b1 !
1#
1'
#375
0#
0'
#376
b1 +
b1 !
1#
1'
#377
0#
0'
#378
b1 +
b1 !
1#
1'
#379
0#
0'
#380
b1 +
b1 !
1#
1'
#381
0#
0'
#382
b1 +
b1 !
1#
1'
#383
0#
0'
#384
b1 +
b1 !
1#
1'
#385
0#
0'
#386
b1 +
b1 !
1#
1'
#387
0#
0'
#388
b1 +
b1 !
1#
1'
#389
0#
0'
#390
b1 +
b1 !
1#
1'
#391
0#
0'
#392
b1 +
b1 !
1#
1'
#393
0#
0'
#394
b1 +
b1 !
1#
1'
#395
0#
0'
#396
b1 +
b1 !
1#
1'
#397
0#
0'
#398
b1 +
b1 !
1#
1'
#399
0#
0'
#400
b1 +
b1 !
1#
1'
#401
0#
0'
#402
b1 +
b1 !
1#
1'
#403
0#
0'
#404
b1 +
b1 !
1#
1'
#405
0#
0'
#406
b1 +
b1 !
1#
1'
#407
0#
0'
#408
b1 +
b1 !
1#
1'
#409
0#
0'
#410
b1 +
b1 !
1#
1'
#411
0#
0'
#412
b1 +
b1 !
1#
1'
#413
0#
0'
#414
b1 +
b1 !
1#
1'
#415
0#
0'
#416
b1 +
b1 !
1#
1'
#417
0#
0'
#418
b1 +
b1 !
1#
1'
#419
0#
0'
#420
b1 +
b1 !
1#
1'
#421
0#
0'
#422
b1 +
b1 !
1#
1'
#423
0#
0'
#424
b1 +
b1 !
1#
1'
#425
0#
0'
#426
b1 +
b1 !
1#
1'
#427
0#
0'
#428
b1 +
b1 !
1#
1'
#429
0#
0'
#430
b1 +
b1 !
1#
1'
#431
0#
0'
#432
b1 +
b1 !
1#
1'
#433
0#
0'
#434
b1 +
b1 !
1#
1'
#435
0#
0'
#436
b1 +
b1 !
1#
1'
#437
0#
0'
#438
b1 +
b1 !
1#
1'
#439
0#
0'
#440
b1 +
b1 !
1#
1'
#441
0#
0'
#442
b1 +
b1 !
1#
1'
#443
0#
0'
#444
b1 +
b1 !
1#
1'
#445
0#
0'
#446
b1 +
b1 !
1#
1'
#447
0#
0'
#448
b1 +
b1 !
1#
1'
#449
0#
0'
#450
b1 +
b1 !
1#
1'
#451
0#
0'
#452
b1 +
b1 !
1#
1'
#453
0#
0'
#454
b1 +
b1 !
1#
1'
#455
0#
0'
#456
b1 +
b1 !
1#
1'
#457
0#
0'
#458
b1 +
b1 !
1#
1'
#459
0#
0'
#460
b1 +
b1 !
1#
1'
#461
0#
0'
#462
b1 +
b1 !
1#
1'
#463
0#
0'
#464
b1 +
b1 !
1#
1'
#465
0#
0'
#466
b1 +
b1 !
1#
1'
#467
0#
0'
#468
b1 +
b1 !
1#
1'
#469
0#
0'
#470
b1 +
b1 !
1#
1'
#471
0#
0'
#472
b1 +
b1 !
1#
1'
#473
0#
0'
#474
b1 +
b1 !
1#
1'
#475
0#
0'
#476
b1 +
b1 !
1#
1'
#477
0#
0'
#478
b1 +
b1 !
1#
1'
#479
0#
0'
#480
b1 +
b1 !
1#
1'
#481
0#
0'
#482
b1 +
b1 !
1#
1'
#483
0#
0'
#484
b1 +
b1 !
1#
1'
#485
0#
0'
#486
b1 +
b1 !
1#
1'
#487
0#
0'
#488
b1 +
b1 !
1#
1'
#489
0#
0'
#490
b1 +
b1 !
1#
1'
#491
0#
0'
#492
b1 +
b1 !
1#
1'
#493
0#
0'
#494
b1 +
b1 !
1#
1'
#495
0#
0'
#496
b1 +
b1 !
1#
1'
#497
0#
0'
#498
b1 +
b1 !
1#
1'
#499
0#
0'
#500
b1 +
b1 !
1#
1'
#501
0#
0'
#502
b1 +
b1 !
1#
1'
#503
0#
0'
#504
b1 +
b1 !
1#
1'
#505
0#
0'
#506
b1 +
b1 !
1#
1'
#507
0#
0'
#508
b1 +
b1 !
1#
1'
#509
0#
0'
#510
b1 +
b1 !
1#
1'
#511
0#
0'
#512
b11111111 +
b11111111 !
1#
1'
1%
1)
#513
0#
0'
#514
b11111111 +
b11111111 !
1#
1'
#515
0#
0'
#516
b11111111 +
b11111111 !
1#
1'
#517
0#
0'
#518
b11111111 +
b11111111 !
1#
1'
#519
0#
0'
#520
b11111111 +
b11111111 !
1#
1'
#521
0#
0'
#522
b11111111 +
b11111111 !
1#
1'
#523
0#
0'
#524
b11111111 +
b11111111 !
1#
1'
#525
0#
0'
#526
b11111111 +
b11111111 !
1#
1'
#527
0#
0'
#528
b11111111 +
b11111111 !
1#
1'
#529
0#
0'
#530
b11111111 +
b11111111 !
1#
1'
#531
0#
0'
#532
b11111111 +
b11111111 !
1#
1'
#533
0#
0'
#534
b11111111 +
b11111111 !
1#
1'
#535
0#
0'
#536
b11111111 +
b11111111 !
1#
1'
#537
0#
0'
#538
b11111111 +
b11111111 !
1#
1'
#539
0#
0'
#540
b11111111 +
b11111111 !
1#
1'
#541
0#
0'
#542
b11111111 +
b11111111 !
1#
1'
#543
0#
0'
#544
b11111111 +
b11111111 !
1#
1'
#545
0#
0'
#546
b11111111 +
b11111111 !
1#
1'
#547
0#
0'
#548
b11111111 +
b11111111 !
1#
1'
#549
0#
0'
#550
b11111111 +
b11111111 !
1#
1'
#551
0#
0'
#552
b11111111 +
b11111111 !
1#
1'
#553
0#
0'
#554
b11111111 +
b11111111 !
1#
1'
#555
0#
0'
#556
b11111111 +
b11111111 !
1#
1'
#557
0#
0'
#558
b11111111 +
b11111111 !
1#
1'
#559
0#
0'
#560
b11111111 +
b11111111 !
1#
1'
#561
0#
0'
#562
b11111111 +
b11111111 !
1#
1'
#563
0#
0'
#564
b11111111 +
b11111111 !
1#
1'
#565
0#
0'
#566
b11111111 +
b11111111 !
1#
1'
#567
0#
0'
#568
b11111111 +
b11111111 !
1#
1'
#569
0#
0'
#570
b11111111 +
b11111111 !
1#
1'
#571
0#
0'
#572
b11111111 +
b11111111 !
1#
1'
#573
0#
0'
#574
b11111111 +
b11111111 !
1#
1'
#575
0#
0'
#576
b11111111 +
b11111111 !
1#
1'
#577
0#
0'
#578
b11111111 +
b11111111 !
1#
1'
#579
0#
0'
#580
b11111111 +
b11111111 !
1#
1'
#581
0#
0'
#582
b11111111 +
b11111111 !
1#
1'
#583
0#
0'
#584
b11111111 +
b11111111 !
1#
1'
#585
0#
0'
#586
b11111111 +
b11111111 !
1#
1'
#587
0#
0'
#588
b11111111 +
b11111111 !
1#
1'
#589
0#
0'
#590
b11111111 +
b11111111 !
1#
1'
#591
0#
0'
#592
b11111111 +
b11111111 !
1#
1'
#593
0#
0'
#594
b11111111 +
b11111111 !
1#
1'
#595
0#
0'
#596
b11111111 +
b11111111 !
1#
1'
#597
0#
0'
#598
b11111111 +
b11111111 !
1#
1'
#599
0#
0'
#600
b11111111 +
b11111111 !
1#
1'
#601
0#
0'
#602
b11111111 +
b11111111 !
1#
1'
#603
0#
0'
#604
b11111111 +
b11111111 !
1#
1'
#605
0#
0'
#606
b11111111 +
b11111111 !
1#
1'
#607
0#
0'
#608
b11111111 +
b11111111 !
1#
1'
#609
0#
0'
#610
b11111111 +
b11111111 !
1#
1'
#611
0#
0'
#612
b11111111 +
b11111111 !
1#
1'
#613
0#
0'
#614
b11111111 +
b11111111 !
1#
1'
#615
0#
0'
#616
b11111111 +
b11111111 !
1#
1'
#617
0#
0'
#618
b11111111 +
b11111111 !
1#
1'
#619
0#
0'
#620
b11111111 +
b11111111 !
1#
1'
#621
0#
0'
#622
b11111111 +
b11111111 !
1#
1'
#623
0#
0'
#624
b11111111 +
b11111111 !
1#
1'
#625
0#
0'
#626
b11111111 +
b11111111 !
1#
1'
#627
0#
0'
#628
b11111111 +
b11111111 !
1#
1'
#629
0#
0'
#630
b11111111 +
b11111111 !
1#
1'
#631
0#
0'
#632
b11111111 +
b11111111 !
1#
1'
#633
0#
0'
#634
b11111111 +
b11111111 !
1#
1'
#635
0#
0'
#636
b11111111 +
b11111111 !
1#
1'
#637
0#
0'
#638
b11111111 +
b11111111 !
1#
1'
#639
0#
0'
#640
b11111111 +
b11111111 !
1#
1'
#641
0#
0'
#642
b11111111 +
b11111111 !
1#
1'
#643
0#
0'
#644
b11111111 +
b11111111 !
1#
1'
#645
0#
0'
#646
b11111111 +
b11111111 !
1#
1'
#647
0#
0'
#648
b11111111 +
b11111111 !
1#
1'
#649
0#
0'
#650
b11111111 +
b11111111 !
1#
1'
#651
0#
0'
#652
b11111111 +
b11111111 !
1#
1'
#653
0#
0'
#654
b11111111 +
b11111111 !
1#
1'
#655
0#
0'
#656
b11111111 +
b11111111 !
1#
1'
#657
0#
0'
#658
b11111111 +
b11111111 !
1#
1'
#659
0#
0'
#660
b11111111 +
b11111111 !
1#
1'
#661
0#
0'
#662
b11111111 +
b11111111 !
1#
1'
#663
0#
0'
#664
b11111111 +
b11111111 !
1#
1'
#665
0#
0'
#666
b11111111 +
b11111111 !
1#
1'
#667
0#
0'
#668
b11111111 +
b11111111 !
1#
1'
#669
0#
0'
#670
b11111111 +
b11111111 !
1#
1'
#671
0#
0'
#672
b11111111 +
b11111111 !
1#
1'
#673
0#
0'
#674
b11111111 +
b11111111 !
1#
1'
#675
0#
0'
#676
b11111111 +
b11111111 !
1#
1'
#677
0#
0'
#678
b11111111 +
b11111111 !
1#
1'
#679
0#
0'
#680
b11111111 +
b11111111 !
1#
1'
#681
0#
0'
#682
b11111111 +
b11111111 !
1#
1'
#683
0#
0'
#684
b11111111 +
b11111111 !
1#
1'
#685
0#
0'
#686
b11111111 +
b11111111 !
1#
1'
#687
0#
0'
#688
b11111111 +
b11111111 !
1#
1'
#689
0#
0'
#690
b11111111 +
b11111111 !
1#
1'
#691
0#
0'
#692
b11111111 +
b11111111 !
1#
1'
#693
0#
0'
#694
b11111111 +
b11111111 !
1#
1'
#695
0#
0'
#696
b11111111 +
b11111111 !
1#
1'
#697
0#
0'
#698
b11111111 +
b11111111 !
1#
1'
#699
0#
0'
#700
b11111111 +
b11111111 !
1#
1'
#701
0#
0'
#702
b11111111 +
b11111111 !
1#
1'
#703
0#
0'
#704
b11111111 +
b11111111 !
1#
1'
#705
0#
0'
#706
b11111111 +
b11111111 !
1#
1'
#707
0#
0'
#708
b11111111 +
b11111111 !
1#
1'
#709
0#
0'
#710
b11111111 +
b11111111 !
1#
1'
#711
0#
0'
#712
b11111111 +
b11111111 !
1#
1'
#713
0#
0'
#714
b11111111 +
b11111111 !
1#
1'
#715
0#
0'
#716
b11111111 +
b11111111 !
1#
1'
#717
0#
0'
#718
b11111111 +
b11111111 !
1#
1'
#719
0#
0'
#720
b11111111 +
b11111111 !
1#
1'
#721
0#
0'
#722
b11111111 +
b11111111 !
1#
1'
#723
0#
0'
#724
b11111111 +
b11111111 !
1#
1'
#725
0#
0'
#726
b11111111 +
b11111111 !
1#
1'
#727
0#
0'
#728
b11111111 +
b11111111 !
1#
1'
#729
0#
0'
#730
b11111111 +
b11111111 !
1#
1'
#731
0#
0'
#732
b11111111 +
b11111111 !
1#
1'
#733
0#
0'
#734
b11111111 +
b11111111 !
1#
1'
#735
0#
0'
#736
b11111111 +
b11111111 !
1#
1'
#737
0#
0'
#738
b11111111 +
b11111111 !
1#
1'
#739
0#
0'
#740
b11111111 +
b11111111 !
1#
1'
#741
0#
0'
#742
b11111111 +
b11111111 !
1#
1'
#743
0#
0'
#744
b11111111 +
b11111111 !
1#
1'
#745
0#
0'
#746
b11111111 +
b11111111 !
1#
1'
#747
0#
0'
#748
b11111111 +
b11111111 !
1#
1'
#749
0#
0'
#750
b11111111 +
b11111111 !
1#
1'
#751
0#
0'
#752
b11111111 +
b11111111 !
1#
1'
#753
0#
0'
#754
b11111111 +
b11111111 !
1#
1'
#755
0#
0'
#756
b11111111 +
b11111111 !
1#
1'
#757
0#
0'
#758
b11111111 +
b11111111 !
1#
1'
#759
0#
0'
#760
b11111111 +
b11111111 !
1#
1'
#761
0#
0'
#762
b11111111 +
b11111111 !
1#
1'
#763
0#
0'
#764
b11111111 +
b11111111 !
1#
1'
#765
0#
0'
#766
b11111111 +
b11111111 !
1#
1'
#767
0#
0'
#768
b11111111 +
b11111111 !
1#
1'
#769
0#
0'
#770
b11111111 +
b11111111 !
1#
1'
#771
0#
0'
#772
b11111111 +
b11111111 !
1#
1'
#773
0#
0'
#774
b11111111 +
b11111111 !
1#
1'
#775
0#
0'
#776
b11111111 +
b11111111 !
1#
1'
#777
0#
0'
#778
b11111111 +
b11111111 !
1#
1'
#779
0#
0'
#780
b11111111 +
b11111111 !
1#
1'
#781
0#
0'
#782
b11111111 +
b11111111 !
1#
1'
#783
0#
0'
#784
b11111111 +
b11111111 !
1#
1'
#785
0#
0'
#786
b11111111 +
b11111111 !
1#
1'
#787
0#
0'
#788
b11111111 +
b11111111 !
1#
1'
#789
0#
0'
#790
b11111111 +
b11111111 !
1#
1'
#791
0#
0'
#792
b11111111 +
b11111111 !
1#
1'
#793
0#
0'
#794
b11111111 +
b11111111 !
1#
1'
#795
0#
0'
#796
b11111111 +
b11111111 !
1#
1'
#797
0#
0'
#798
b11111111 +
b11111111 !
1#
1'
#799
0#
0'
#800
b11111111 +
b11111111 !
1#
1'
#801
0#
0'
#802
b11111111 +
b11111111 !
1#
1'
#803
0#
0'
#804
b11111111 +
b11111111 !
1#
1'
#805
0#
0'
#806
b11111111 +
b11111111 !
1#
1'
#807
0#
0'
#808
b11111111 +
b11111111 !
1#
1'
#809
0#
0'
#810
b11111111 +
b11111111 !
1#
1'
#811
0#
0'
#812
b11111111 +
b11111111 !
1#
1'
#813
0#
0'
#814
b11111111 +
b11111111 !
1#
1'
#815
0#
0'
#816
b11111111 +
b11111111 !
1#
1'
#817
0#
0'
#818
b11111111 +
b11111111 !
1#
1'
#819
0#
0'
#820
b11111111 +
b11111111 !
1#
1'
#821
0#
0'
#822
b11111111 +
b11111111 !
1#
1'
#823
0#
0'
#824
b11111111 +
b11111111 !
1#
1'
#825
0#
0'
#826
b11111111 +
b11111111 !
1#
1'
#827
0#
0'
#828
b11111111 +
b11111111 !
1#
1'
#829
0#
0'
#830
b11111111 +
b11111111 !
1#
1'
#831
0#
0'
#832
b11111111 +
b11111111 !
1#
1'
#833
0#
0'
#834
b11111111 +
b11111111 !
1#
1'
#835
0#
0'
#836
b11111111 +
b11111111 !
1#
1'
#837
0#
0'
#838
b11111111 +
b11111111 !
1#
1'
#839
0#
0'
#840
b11111111 +
b11111111 !
1#
1'
#841
0#
0'
#842
b11111111 +
b11111111 !
1#
1'
#843
0#
0'
#844
b11111111 +
b11111111 !
1#
1'
#845
0#
0'
#846
b11111111 +
b11111111 !
1#
1'
#847
0#
0'
#848
b11111111 +
b11111111 !
1#
1'
#849
0#
0'
#850
b11111111 +
b11111111 !
1#
1'
#851
0#
0'
#852
b11111111 +
b11111111 !
1#
1'
#853
0#
0'
#854
b11111111 +
b11111111 !
1#
1'
#855
0#
0'
#856
b11111111 +
b11111111 !
1#
1'
#857
0#
0'
#858
b11111111 +
b11111111 !
1#
1'
#859
0#
0'
#860
b11111111 +
b11111111 !
1#
1'
#861
0#
0'
#862
b11111111 +
b11111111 !
1#
1'
#863
0#
0'
#864
b11111111 +
b11111111 !
1#
1'
#865
0#
0'
#866
b11111111 +
b11111111 !
1#
1'
#867
0#
0'
#868
b11111111 +
b11111111 !
1#
1'
#869
0#
0'
#870
b11111111 +
b11111111 !
1#
1'
#871
0#
0'
#872
b11111111 +
b11111111 !
1#
1'
#873
0#
0'
#874
b11111111 +
b11111111 !
1#
1'
#875
0#
0'
#876
b11111111 +
b11111111 !
1#
1'
#877
0#
0'
#878
b11111111 +
b11111111 !
1#
1'
#879
0#
0'
#880
b11111111 +
b11111111 !
1#
1'
#881
0#
0'
#882
b11111111 +
b11111111 !
1#
1'
#883
0#
0'
#884
b11111111 +
b11111111 !
1#
1'
#885
0#
0'
#886
b11111111 +
b11111111 !
1#
1'
#887
0#
0'
#888
b11111111 +
b11111111 !
1#
1'
#889
0#
0'
#890
b11111111 +
b11111111 !
1#
1'
#891
0#
0'
#892
b11111111 +
b11111111 !
1#
1'
#893
0#
0'
#894
b11111111 +
b11111111 !
1#
1'
#895
0#
0'
#896
b11111111 +
b11111111 !
1#
1'
#897
0#
0'
#898
b11111111 +
b11111111 !
1#
1'
#899
0#
0'
#900
b11111111 +
b11111111 !
1#
1'
#901
0#
0'
#902
b11111111 +
b11111111 !
1#
1'
#903
0#
0'
#904
b11111111 +
b11111111 !
1#
1'
#905
0#
0'
#906
b11111111 +
b11111111 !
1#
1'
#907
0#
0'
#908
b11111111 +
b11111111 !
1#
1'
#909
0#
0'
#910
b11111111 +
b11111111 !
1#
1'
#911
0#
0'
#912
b11111111 +
b11111111 !
1#
1'
#913
0#
0'
#914
b11111111 +
b11111111 !
1#
1'
#915
0#
0'
#916
b11111111 +
b11111111 !
1#
1'
#917
0#
0'
#918
b11111111 +
b11111111 !
1#
1'
#919
0#
0'
#920
b11111111 +
b11111111 !
1#
1'
#921
0#
0'
#922
b11111111 +
b11111111 !
1#
1'
#923
0#
0'
#924
b11111111 +
b11111111 !
1#
1'
#925
0#
0'
#926
b11111111 +
b11111111 !
1#
1'
#927
0#
0'
#928
b11111111 +
b11111111 !
1#
1'
#929
0#
0'
#930
b11111111 +
b11111111 !
1#
1'
#931
0#
0'
#932
b11111111 +
b11111111 !
1#
1'
#933
0#
0'
#934
b11111111 +
b11111111 !
1#
1'
#935
0#
0'
#936
b11111111 +
b11111111 !
1#
1'
#937
0#
0'
#938
b11111111 +
b11111111 !
1#
1'
#939
0#
0'
#940
b11111111 +
b11111111 !
1#
1'
#941
0#
0'
#942
b11111111 +
b11111111 !
1#
1'
#943
0#
0'
#944
b11111111 +
b11111111 !
1#
1'
