upcounter.v
module syncounter8( clock, reset, enable, count_out);

input clock, reset, enable;
output [7:0] count_out;

wire clock, reset, enable;
reg [7:0] count_out;

always @(posedge clock) 
begin
  
   if(reset == 1'b1) 
      begin
        count_out<= #1 8'b00000000;
      end

   else if(enable == 1'b1)
      begin
        count_out<= #1 count_out + 1'b1;
      end
end

endmodule

upcounter_tb.v
`include "upcounter.v"
module syncount_tb;

reg clock, reset, enable;
wire[7:0] count_out;

syncounter8 t_b(.clock(clock), .reset(reset), .enable(enable), .count_out(count_out));

initial begin
   
   clock = 1;
   reset = 0;
   enable = 0;

   #5 reset = 1;
   #10 reset = 0;
   #10 enable = 1;
   #200 enable = 0;
   #5 $finish;

end

always begin
#5 clock = ~clock;
end

initial begin

   $dumpfile("test1co.vcd");
   $dumpvars(0,syncount_tb);
   $display("time    clk reset enable counter");
   $monitor("%g    %b %b %b %b",$time, clock, reset, enable, count_out);

end

endmodule

test1co.vcd
$date
	Thu Nov  8 16:42:23 2018
$end
$version
	Icarus Verilog
$end
$timescale
	1s
$end
$scope module syncount_tb $end
$var wire 8 ! count_out [7:0] $end
$var reg 1 " clock $end
$var reg 1 # enable $end
$var reg 1 $ reset $end
$scope module t_b $end
$var wire 1 % clock $end
$var wire 1 & enable $end
$var wire 1 ' reset $end
$var reg 8 ( count_out [7:0] $end
$upscope $end
$upscope $end
$enddefinitions $end
#0
$dumpvars
bx (
0'
0&
1%
0$
0#
1"
bx !
$end
#5
0"
0%
1$
1'
#10
1"
1%
#11
b0 (
b0 !
#15
0"
0%
0$
0'
#20
1"
1%
#25
0"
0%
1#
1&
#30
1"
1%
#31
b1 (
b1 !
#35
0"
0%
#40
1"
1%
#41
b10 (
b10 !
#45
0"
0%
#50
1"
1%
#51
b11 (
b11 !
#55
0"
0%
#60
1"
1%
#61
b100 (
b100 !
#65
0"
0%
#70
1"
1%
#71
b101 (
b101 !
#75
0"
0%
#80
1"
1%
#81
b110 (
b110 !
#85
0"
0%
#90
1"
1%
#91
b111 (
b111 !
#95
0"
0%
#100
1"
1%
#101
b1000 (
b1000 !
#105
0"
0%
#110
1"
1%
#111
b1001 (
b1001 !
#115
0"
0%
#120
1"
1%
#121
b1010 (
b1010 !
#125
0"
0%
#130
1"
1%
#131
b1011 (
b1011 !
#135
0"
0%
#140
1"
1%
#141
b1100 (
b1100 !
#145
0"
0%
#150
1"
1%
#151
b1101 (
b1101 !
#155
0"
0%
#160
1"
1%
#161
b1110 (
b1110 !
#165
0"
0%
#170
1"
1%
#171
b1111 (
b1111 !
#175
0"
0%
#180
1"
1%
#181
b10000 (
b10000 !
#185
0"
0%
#190
1"
1%
#191
b10001 (
b10001 !
#195
0"
0%
#200
1"
1%
#201
b10010 (
b10010 !
#205
0"
0%
#210
1"
1%
#211
b10011 (
b10011 !
#215
0"
0%
#220
1"
1%
#221
b10100 (
b10100 !
#225
0"
0%
0#
0&
