seq.v
module seq(clk,rst,in,out);
input clk,rst,in;
output out;
reg[1:0] state;
reg out;

always @ (posedge clk, posedge rst) begin
if(rst)
state<=2'b00;
else
begin
  case(state)
  2'b00: begin
  if(in==0) state<=2'b01;
  else state<=2'b10;
  end
  2'b01: begin
  if(in) state<=2'b01;
  else state<=2'b10;
  end
  2'b10: begin
  if(in) state<=2'b10;
  else state<=2'b10;
  end
  endcase
  end
 end
 
 always @(posedge clk,posedge rst) begin
 if(rst)
  out<=0;
 else if (state==2'b01)
  out<=1;
 else
   out<=0;
 end
 endmodule

seq_tb.v
`include "seq.v"
module seq_test;
reg clk, rst, in;
wire out;
reg[15:0] sequence;
integer i;

seq dut(clk,rst,in,out);

initial begin
 $dumpfile("testseq.vcd");
 $dumpvars(0,seq_test);
 clk=0;
 rst=1;
 sequence=16'b0110010111011110;
 #5 rst=0;
 for(i=0;i<=15;i=i+1) begin
  in =sequence[i];
  #2 clk=1;
  #2 clk=0;
  $display("State= ", dut.state, " Input= ", in," Output= ", out);
  end
 end 
 endmodule

testseq.vcd
$date
	Thu Nov  8 17:53:08 2018
$end
$version
	Icarus Verilog
$end
$timescale
	1s
$end
$scope module seq_test $end
$var wire 1 ! out $end
$var reg 1 " clk $end
$var integer 32 # i [31:0] $end
$var reg 1 $ in $end
$var reg 1 % rst $end
$var reg 16 & sequence [15:0] $end
$scope module dut $end
$var wire 1 ' clk $end
$var wire 1 ( in $end
$var wire 1 ) rst $end
$var reg 1 * out $end
$var reg 2 + state [1:0] $end
$upscope $end
$upscope $end
$enddefinitions $end
#0
$dumpvars
b0 +
0*
1)
x(
0'
b110010111011110 &
1%
x$
bx #
0"
0!
$end
#5
0$
0(
b0 #
0%
0)
#7
b1 +
1"
1'
#9
1$
1(
b1 #
0"
0'
#11
1*
1!
1"
1'
#13
b10 #
0"
0'
#15
1"
1'
#17
b11 #
0"
0'
#19
1"
1'
#21
b100 #
0"
0'
#23
1"
1'
#25
0$
0(
b101 #
0"
0'
#27
b10 +
1"
1'
#29
1$
1(
b110 #
0"
0'
#31
0*
0!
1"
1'
#33
b111 #
0"
0'
#35
1"
1'
#37
b1000 #
0"
0'
#39
1"
1'
#41
0$
0(
b1001 #
0"
0'
#43
1"
1'
#45
1$
1(
b1010 #
0"
0'
#47
1"
1'
#49
0$
0(
b1011 #
0"
0'
#51
1"
1'
#53
b1100 #
0"
0'
#55
1"
1'
#57
1$
1(
b1101 #
0"
0'
#59
1"
1'
#61
b1110 #
0"
0'
#63
1"
1'
#65
0$
0(
b1111 #
0"
0'
#67
1"
1'
#69
b10000 #
0"
0'
