twobyonemuxtrans.v
module cmos_twobyonemuxtrans(a,b,s,y);
input a,b,s;
output y;
wire x;
supply0 gnd;
supply1 vdd;

//complement s
pmos(x,vdd,s);
nmos(x,gnd,s);

pmos(y,a,x);
nmos(y,a,s);

pmos(y,b,x);
nmos(y,b,s);

endmodule

twobyonemuxtrans_tb.v
`include "twobyonemuxtrans.v"

module twobyonemuxtranstb();
reg a1,b1,s1;
wire out;
initial begin
$dumpfile("twobyonemuxtrans_tb.vcd");
$dumpvars(0,twobyonemuxtranstb);
$display("in1,in2,gate,out");
$monitor("%b,%b,%b,%b",a1,b1,s1,out);
#20 a1=0;b1=0;s1=0;
#20 a1=1;b1=0;s1=0;
#20 a1=0;b1=1;s1=0;
#20 a1=1;b1=1;s1=0;
#20 a1=0;b1=0;s1=1;
#20 a1=1;b1=0;s1=1;
#20 a1=0;b1=1;s1=1;
#20 a1=1;b1=1;s1=1;
#20 $finish;
end

cmos_twobyonemuxtrans n(
.a(a1),
.b(b1),
.s(s1),
.y(out)
);
endmodule

twobyonemuxtrans_tb.vcd
$date
	Thu Nov  8 04:48:52 2018
$end
$version
	Icarus Verilog
$end
$timescale
	1s
$end
$scope module twobyonemuxtranstb $end
$var wire 1 ! out $end
$var reg 1 " a1 $end
$var reg 1 # b1 $end
$var reg 1 $ s1 $end
$scope module n $end
$var wire 1 % a $end
$var wire 1 & b $end
$var wire 1 ' gnd $end
$var wire 1 ( s $end
$var wire 1 ) vdd $end
$var wire 1 * x $end
$var wire 1 ! y $end
$upscope $end
$upscope $end
$enddefinitions $end
#0
$dumpvars
x*
1)
x(
0'
x&
x%
x$
x#
x"
x!
$end
#20
0$
1*
0(
0#
z!
0&
0"
0%
#40
1"
1%
#60
1#
1&
0"
0%
#80
1"
1%
#100
1$
0*
0!
1(
0#
0&
0"
0%
#120
1"
x!
1%
#140
1#
1&
0"
x!
0%
#160
1"
1!
1%
